jupyter_papermill/__init__.py
jupyter_papermill/_version.py
jupyter_papermill/handlers.py
jupyter_papermill/tests/__init__.py
jupyter_papermill/tests/test_handlers.py
jupyter_papermill-0.0.2.data/data/etc/jupyter/jupyter_notebook_config.d/jupyter_papermill.json
jupyter_papermill-0.0.2.data/data/etc/jupyter/jupyter_server_config.d/jupyter_papermill.json
jupyter_papermill-0.0.2.data/data/share/jupyter/labextensions/@datalayer/jupyter-papermill/build_log.json
jupyter_papermill-0.0.2.data/data/share/jupyter/labextensions/@datalayer/jupyter-papermill/package.json
jupyter_papermill-0.0.2.data/data/share/jupyter/labextensions/@datalayer/jupyter-papermill/schemas/@datalayer/jupyter-papermill/package.json.orig
jupyter_papermill-0.0.2.data/data/share/jupyter/labextensions/@datalayer/jupyter-papermill/schemas/@datalayer/jupyter-papermill/plugin.json
jupyter_papermill-0.0.2.data/data/share/jupyter/labextensions/@datalayer/jupyter-papermill/static/design_icons_lib_index_js.876ae87651999ca1b434.js
jupyter_papermill-0.0.2.data/data/share/jupyter/labextensions/@datalayer/jupyter-papermill/static/design_icons_lib_index_js.876ae87651999ca1b434.js.map
jupyter_papermill-0.0.2.data/data/share/jupyter/labextensions/@datalayer/jupyter-papermill/static/lib_index_js.2d1c42ba56fc225ca4e6.js
jupyter_papermill-0.0.2.data/data/share/jupyter/labextensions/@datalayer/jupyter-papermill/static/lib_index_js.2d1c42ba56fc225ca4e6.js.map
jupyter_papermill-0.0.2.data/data/share/jupyter/labextensions/@datalayer/jupyter-papermill/static/remoteEntry.3e635dab07909aafc4af.js
jupyter_papermill-0.0.2.data/data/share/jupyter/labextensions/@datalayer/jupyter-papermill/static/remoteEntry.3e635dab07909aafc4af.js.map
jupyter_papermill-0.0.2.data/data/share/jupyter/labextensions/@datalayer/jupyter-papermill/static/style.js
jupyter_papermill-0.0.2.data/data/share/jupyter/labextensions/@datalayer/jupyter-papermill/static/style_index_js.6c820f4f7ac681c4fd37.js
jupyter_papermill-0.0.2.dist-info/METADATA
jupyter_papermill-0.0.2.dist-info/WHEEL
jupyter_papermill-0.0.2.dist-info/licenses/LICENSE
jupyter_papermill-0.0.2.dist-info/RECORD
